<?xml version="1.0" encoding="UTF-8"?>
<objects serializationModel="Studio.02.02.00">
	<object class="AudioFile" id="{289fdebb-2728-450c-9bce-d777c0a00bfa}">
		<property name="assetPath">
			<value>stepsforfmod/kuvshinki/k kuvshinkiprig.wav</value>
		</property>
		<property name="frequencyInKHz">
			<value>48</value>
		</property>
		<property name="channelCount">
			<value>2</value>
		</property>
		<property name="length">
			<value>0.64516666666666667</value>
		</property>
		<relationship name="masterAssetFolder">
			<destination>{831bddc3-b990-4526-be1a-093163b34eba}</destination>
		</relationship>
	</object>
</objects>
